my_bgg/__init__.py
my_bgg/cli.py
my_bgg-0.0.0.dist-info/METADATA
my_bgg-0.0.0.dist-info/WHEEL
my_bgg-0.0.0.dist-info/entry_points.txt
my_bgg-0.0.0.dist-info/top_level.txt
my_bgg-0.0.0.dist-info/RECORD
